migrator/__init__.py
migrator/dynamodb_migrator.py
migrator/exceptions/MigratorException.py
migrator/exceptions/MigratorScriptException.py
migrator/exceptions/__init__.py
migrator/steps/AddIndexStep.py
migrator/steps/BaseStep.py
migrator/steps/CreateTableStep.py
migrator/steps/Step.py
migrator/steps/__init__.py
migrator/utilities/AwsUtilities.py
migrator/utilities/DynamoDButilities.py
migrator/utilities/IAMutilities.py
migrator/utilities/LambdaUtilities.py
migrator/utilities/Utilities.py
migrator/utilities/__init__.py
src/migrator/__init__.py
src/migrator/dynamodb_migrator.py
dynamodb_migrator-0.0.8.dist-info/LICENSE
dynamodb_migrator-0.0.8.dist-info/METADATA
dynamodb_migrator-0.0.8.dist-info/WHEEL
dynamodb_migrator-0.0.8.dist-info/top_level.txt
dynamodb_migrator-0.0.8.dist-info/RECORD
