Metadata-Version: 2.1
Name: dynamodb-migrator
Version: 0.0.8
Summary: Library that helps you create and migrate DynamoDB databases
Home-page: https://github.com/bblommers/dynamodb-migrator
Author: Bert Blommers
Author-email: info@bertblommers.nl
License: UNKNOWN
Platform: UNKNOWN
Classifier: Programming Language :: Python :: 3
Classifier: Intended Audience :: Developers
Classifier: License :: OSI Approved :: MIT License
Classifier: Operating System :: OS Independent
Classifier: Topic :: Software Development :: Libraries
Classifier: Topic :: Utilities
Requires-Python: >=3.6
Requires-Dist: tenacity
